<?xml version="1.0" encoding="UTF-8"?>
<knimeNode icon="./default.png" type="Source" xmlns="http://knime.org/node/v2.8" xmlns:xsi="http://www.w3.org/2001/XMLSchema-instance" xsi:schemaLocation="http://knime.org/node/v2.10 http://knime.org/node/v2.10.xsd">
    <name>AdditionalModalityPreprocessor</name>
    
    <shortDescription>
        Read new modality in CSV file format and generates output for AddModality node
    </shortDescription>
    
    <fullDescription>
        <intro>Read new modality in CSV file format and generates output for AddModality node</intro>
        
        <option name="Input CSV File">Input CSV file to be read.</option>
    </fullDescription>
    
    <ports>
        <outPort index="0" name="Modality List">modality data of each molecule.</outPort>
    </ports>    
</knimeNode>
